amazon_bedrock/__init__.py
amazon_bedrock/_client.py
amazon_bedrock/_utils/__init__.py
amazon_bedrock/_utils/_transform.py
amazon_bedrock/resources/__init__.py
amazon_bedrock/resources/api_resource.py
amazon_bedrock/resources/messages.py
amazon_bedrock/resources/models.py
amazon_bedrock/types/__init__.py
amazon_bedrock/types/content_block.py
amazon_bedrock/types/message.py
amazon_bedrock/types/message_param.py
amazon_bedrock/types/text_block.py
amazon_bedrock/types/text_block_param.py
amazon_bedrock-0.0.5.dist-info/METADATA
amazon_bedrock-0.0.5.dist-info/WHEEL
amazon_bedrock-0.0.5.dist-info/entry_points.txt
amazon_bedrock-0.0.5.dist-info/licenses/LICENSE
amazon_bedrock-0.0.5.dist-info/RECORD
